{
  "data": {
    "type": "destination",
    "id": "20140208_colombia_cali",
    "attributes": {
      "latitude": 3.4205556,
      "longitude": -76.5222222,
      "date": "20140208",
      "city": "Cali",
      "country": "Colombia",
      "flickr-link": "72157640800768693",
      "body": "<p>I know for a fact that I didn&#39;t get a full Cali experience. Part of it is that I&#39;m sprinting for the border...</p>\n<p>I walked around to do a number of small errands. It&#39;s not a super pretty city, at least not the side of it I saw. I wish I had gotten to spend some time checking out some of the salsa dancing while I was there. But one of the days I was there, was Sunday, and on Sunday there is nobody in town. Completely empty, walking around reminded me of the beginning of 28 days later. It felt deserted.</p>\n",
      "flickr-cache": {
        "photos": [
          {
            "title": "Cali Traffic",
            "taken": "2014-02-10 11:32:28",
            "description": "I grabbed one sad snap on my way out of town, this was it. Frankly, Cali wasn't a very pretty city, though maybe I just didn't find the right spots. ",
            "versions": [
              {
                "name": "12445655404-75x75-Square.jpg",
                "path": "tmp/72157640800768693/12445655404-75x75-Square.jpg",
                "width": 75,
                "height": 75,
                "label": "Square"
              },
              {
                "name": "12445655404-150x150-Large Square.jpg",
                "path": "tmp/72157640800768693/12445655404-150x150-Large Square.jpg",
                "width": "150",
                "height": "150",
                "label": "Large Square"
              },
              {
                "name": "12445655404-100x75-Thumbnail.jpg",
                "path": "tmp/72157640800768693/12445655404-100x75-Thumbnail.jpg",
                "width": "100",
                "height": "75",
                "label": "Thumbnail"
              },
              {
                "name": "12445655404-240x180-Small.jpg",
                "path": "tmp/72157640800768693/12445655404-240x180-Small.jpg",
                "width": "240",
                "height": "180",
                "label": "Small"
              },
              {
                "name": "12445655404-320x240-Small 320.jpg",
                "path": "tmp/72157640800768693/12445655404-320x240-Small 320.jpg",
                "width": "320",
                "height": 240,
                "label": "Small 320"
              },
              {
                "name": "12445655404-500x375-Medium.jpg",
                "path": "tmp/72157640800768693/12445655404-500x375-Medium.jpg",
                "width": "500",
                "height": "375",
                "label": "Medium"
              },
              {
                "name": "12445655404-640x480-Medium 640.jpg",
                "path": "tmp/72157640800768693/12445655404-640x480-Medium 640.jpg",
                "width": "640",
                "height": "480",
                "label": "Medium 640"
              },
              {
                "name": "12445655404-800x600-Medium 800.jpg",
                "path": "tmp/72157640800768693/12445655404-800x600-Medium 800.jpg",
                "width": "800",
                "height": 600,
                "label": "Medium 800"
              },
              {
                "name": "12445655404-1024x768-Large.jpg",
                "path": "tmp/72157640800768693/12445655404-1024x768-Large.jpg",
                "width": "1024",
                "height": "768",
                "label": "Large"
              },
              {
                "name": "12445655404-1600x1200-Large 1600.jpg",
                "path": "tmp/72157640800768693/12445655404-1600x1200-Large 1600.jpg",
                "width": "1600",
                "height": 1200,
                "label": "Large 1600"
              },
              {
                "name": "12445655404-2048x1536-Large 2048.jpg",
                "path": "tmp/72157640800768693/12445655404-2048x1536-Large 2048.jpg",
                "width": "2048",
                "height": 1536,
                "label": "Large 2048"
              },
              {
                "name": "12445655404-3264x2448-Original.jpg",
                "path": "tmp/72157640800768693/12445655404-3264x2448-Original.jpg",
                "width": "3264",
                "height": "2448",
                "label": "Original"
              }
            ]
          }
        ],
        "title": "Colombia, Cali"
      }
    }
  }
}
